GxGVTL.cti
GxU3VTL.cti
GxUSBTL.cti
PyRVC.cpython-36m-x86_64-linux-gnu.so
libCLAllSerial_gcc485_v3_0.so
libCLProtocol_gcc485_v3_0.so
libCLSerCOM.so
libCLSerHvc.so
libFirmwareUpdate_gcc_v3_1_Basler_pylon.so
libFormatConversion.so
libGCBase_gcc485_v3_0.so
libGCBase_gcc_v3_1_Basler_pylon.so
libGenApi_gcc_v3_1_Basler_pylon.so
libGenCP_gcc485_v3_0.so
libLog_gcc485_v3_0.so
libLog_gcc_v3_1_Basler_pylon.so
libMVFGControl.so
libMVGigEVisionSDK.so
libMVGigEVisionSDK.so.4.6.0.3
libMVRender.so
libMathParser_gcc_v3_1_Basler_pylon.so
libMediaProcess.so
libMvCamLVision.so
libMvCamLVision.so.4.6.0.3
libMvCameraControl.so
libMvCameraControl.so.4.6.0.3
libMvCameraControlWrapper.so
libMvCameraControlWrapper.so.4.5.0.1
libMvSDKVersion.so
libMvUsb3vTL.so
libMvUsb3vTL.so.4.6.0.3
libNodeMapData_gcc_v3_1_Basler_pylon.so
libRVC.so
libRVC.so.1
libRVC.so.1.14.0
libXmlParser_gcc_v3_1_Basler_pylon.so
libavutil.so
libbxapi-6.2.0.so
libgxapi-6.2.0.so
libgxiapi.so
liblog4cpp_gcc485_v3_0.so
liblog4cpp_gcc_v3_1_Basler_pylon.so
libpylon_TL_bcon-6.2.0.so
libpylon_TL_camemu-6.2.0.so
libpylon_TL_gige-6.2.0.so
libpylon_TL_gtc-6.2.0.so
libpylon_TL_usb-6.2.0.so
libpylonbase-6.2.0.so
libpylonc-6.2.0.so
libpylonutility-6.2.0.so
libswscale.so
libudev.so
libusb-1.0.so
libusb-1.0.so.0
libuxapi-6.2.0.so
pylon-libusb-1.0.so
PyRVC-1.14.0.dist-info/METADATA
PyRVC-1.14.0.dist-info/WHEEL
PyRVC-1.14.0.dist-info/top_level.txt
PyRVC-1.14.0.dist-info/RECORD
