Metadata-Version: 2.1
Name: PyRVC
Version: 1.14.0
Summary: Rvbust RVC Camera Python SDK
Home-page: UNKNOWN
Author: rvbust
Author-email: 
License: UNKNOWN
Platform: UNKNOWN
Classifier: Programming Language :: Python :: 3
Classifier: License :: OSI Approved :: MIT License
Requires-Python: >=3
